{
  "开场": {
    "cap": "寻找过去的回忆",
    "pgrs": 1.0,
    "dia": [
      {
        "id": 10000,
        "txt": "你觉得忘记和死亡 谁更残酷",
        "opt": {
          "死亡": [
            {
              "id": 10001,
              "chr": "0",
              "txt": "是么 我觉得忘记更加残酷"
            }
          ],
          "忘记吧": [
            {
              "id": 10002,
              "opt": {
                "我...害怕忘记": [
                  {
                    "id": 10003,
                    "chr": 0,
                    "txt": "好吧 我会帮你记住的"
                  }
                ]
              }
            }
          ]
        }
      },
      {
        "id": 10004,
        "txt": "但是，不是所有的回忆都值得被记住吧？",
        "opt": {
          "也许吧": [
            {
              "id": 10005,
              "chr": "1",
              "txt": "那些痛苦的回忆，我宁愿忘记。"
            }
          ],
          "每一段回忆都珍贵": [
            {
              "id": 10006,
              "chr": "1",
              "txt": "即使痛苦，它们也塑造了现在的我。"
            }
          ]
        }
      }
    ]
  },
  "回忆碎片": {
    "cap": "拼凑破碎的记忆",
    "pgrs": 2.0,
    "dia": [
      {
        "id": 20000,
        "txt": "这片森林...你觉得它有什么熟悉的地方吗？",
        "opt": {
          "熟悉": [
            {
              "id": 20001,
              "chr": "1",
              "txt": "是的，我记得小时候曾来过这里。"
            }
          ],
          "不太记得": [
            {
              "id": 20002,
              "chr": "1",
              "txt": "也许只是我的错觉吧。"
            }
          ]
        }
      },
      {
        "id": 20003,
        "txt": "你曾经在这里埋藏了什么东西，记得吗？",
        "opt": {
          "记得": [
            {
              "id": 20004,
              "chr": "1",
              "txt": "是的，我藏了一些重要的东西。",
              "opt": {
                "是什么东西": [
                  {
                    "id": 20005,
                    "chr": "0",
                    "txt": "一个木盒，里面装满了儿时的梦想。"
                  }
                ],
                "你为什么要藏起来": [
                  {
                    "id": 20006,
                    "chr": "0",
                    "txt": "因为那时的我害怕失去这些梦想。"
                  }
                ]
              }
            }
          ],
          "不记得了": [
            {
              "id": 20007,
              "chr": "1",
              "txt": "我真的不记得了，也许它已经消失在时光中了。",
              "opt": {
                "那要去找找看吗": [
                  {
                    "id": 20008,
                    "chr": "0",
                    "txt": "也许可以，但我不确定是否能找到。"
                  }
                ],
                "放弃寻找": [
                  {
                    "id": 20009,
                    "chr": "0",
                    "txt": "也许有些回忆不该被唤醒。"
                  }
                ]
              }
            }
          ]
        }
      },
      {
        "id": 20010,
        "txt": "你觉得这片森林和当年相比，变了吗？",
        "opt": {
          "变了": [
            {
              "id": 20011,
              "chr": "1",
              "txt": "一切都变了，连空气都不再熟悉。",
              "opt": {
                "为什么觉得变了": [
                  {
                    "id": 20012,
                    "chr": "0",
                    "txt": "我想是因为我自己变了，过去的那个我已经不复存在。"
                  }
                ],
                "你是否想念以前的样子": [
                  {
                    "id": 20013,
                    "chr": "0",
                    "txt": "有时候会想念，但我知道过去无法回头。"
                  }
                ]
              }
            }
          ],
          "没有变": [
            {
              "id": 20014,
              "chr": "1",
              "txt": "不，森林还是原来的模样，只有我在变。",
              "opt": {
                "这让你感到难过吗": [
                  {
                    "id": 20015,
                    "chr": "0",
                    "txt": "是的，有时候我觉得自己被遗忘了。"
                  }
                ],
                "这是否意味着你找回了什么": [
                  {
                    "id": 20016,
                    "chr": "0",
                    "txt": "也许吧，我找回了那个曾经在这里嬉戏的自己。"
                  }
                ]
              }
            }
          ]
        }
      }
    ]
  },
  "深渊": {
    "cap": "进入未知的深渊",
    "pgrs": 3.0,
    "dia": [
      {
        "id": 30000,
        "txt": "前方有一条黑暗的小路，你决定要走下去吗？",
        "opt": {
          "继续前进": [
            {
              "id": 30001,
              "chr": "1",
              "txt": "是的，我必须知道这条路的尽头。",
              "opt": {
                "为什么": [
                  {
                    "id": 30002,
                    "chr": "0",
                    "txt": "因为只有这样，我才能解开所有的谜团。"
                  }
                ],
                "你不害怕吗": [
                  {
                    "id": 30003,
                    "chr": "0",
                    "txt": "害怕，但我别无选择。"
                  }
                ]
              }
            }
          ],
          "放弃": [
            {
              "id": 30004,
              "chr": "1",
              "txt": "我觉得这条路太危险了，我们还是回头吧。",
              "opt": {
                "你确定吗": [
                  {
                    "id": 30005,
                    "chr": "0",
                    "txt": "是的，也许有些秘密不值得冒险。"
                  }
                ],
                "这可能是最后的机会": [
                  {
                    "id": 30006,
                    "chr": "0",
                    "txt": "也许吧，但我不想冒这个险。"
                  }
                ]
              }
            }
          ]
        }
      },
      {
        "id": 30007,
        "txt": "走在小路上，你听到了一些奇怪的声音...",
        "opt": {
          "停下来听": [
            {
              "id": 30008,
              "chr": "1",
              "txt": "这些声音是从哪里传来的？",
              "opt": {
                "继续听": [
                  {
                    "id": 30009,
                    "chr": "0",
                    "txt": "它们越来越清晰，好像有人在低语。"
                  }
                ],
                "快走": [
                  {
                    "id": 30010,
                    "chr": "0",
                    "txt": "不，我必须离开这里，这里不安全。"
                  }
                ]
              }
            }
          ],
          "忽略声音": [
            {
              "id": 30011,
              "chr": "1",
              "txt": "不管它们是什么，我不能被分心。",
              "opt": {
                "继续走": [
                  {
                    "id": 30012,
                    "chr": "0",
                    "txt": "我必须保持专注，这条路不会轻易让我通过。"
                  }
                ]
              }
            }
          ]
        }
      },
      {
        "id": 30013,
        "txt": "前方出现了一道裂缝，你要怎么跨过去？",
        "opt": {
          "跳过去": [
            {
              "id": 30014,
              "chr": "1",
              "txt": "我得小心点，但我会试着跳过去。",
              "opt": {
                "跳跃成功": [
                  {
                    "id": 30015,
                    "chr": "0",
                    "txt": "我成功了，现在继续前进。"
                  }
                ],
                "跳跃失败": [
                  {
                                      "id": 30016,
                  "chr": "0",
                  "txt": "糟了，我失足了！",
                  "opt": {
                    "求救": [
                      {
                        "id": 30017,
                        "chr": "1",
                        "txt": "有人吗？帮帮我！",
                        "opt": {
                          "无人回应": [
                            {
                              "id": 30018,
                              "chr": "0",
                              "txt": "没有人回应，我必须自己想办法。"
                            }
                          ],
                          "有人出现": [
                            {
                              "id": 30019,
                              "chr": "0",
                              "txt": "一个陌生的声音响起：'你还好吗？需要帮忙吗？'",
                              "opt": {
                                "接受帮助": [
                                  {
                                    "id": 30020,
                                    "chr": "1",
                                    "txt": "是的，拜托，帮我上去！",
                                    "opt": {
                                      "成功获救": [
                                        {
                                          "id": 30021,
                                          "chr": "0",
                                          "txt": "谢谢你！我不知道该如何报答。"
                                        }
                                      ],
                                      "再遇险": [
                                        {
                                          "id": 30022,
                                          "chr": "0",
                                          "txt": "刚被拉上来，脚下又开始崩塌！"
                                        }
                                      ]
                                    }
                                  }
                                ],
                                "拒绝帮助": [
                                  {
                                    "id": 30023,
                                    "chr": "1",
                                    "txt": "不，我得自己搞定。",
                                    "opt": {
                                      "自救成功": [
                                        {
                                          "id": 30024,
                                          "chr": "0",
                                          "txt": "终于，我成功抓住了岩石，爬了上来。"
                                        }
                                      ],
                                      "自救失败": [
                                        {
                                          "id": 30025,
                                          "chr": "0",
                                          "txt": "我尽力了，但最终我还是掉进了裂缝中。"
                                        }
                                      ]
                                    }
                                  }
                                ]
                              }
                            }
                          ]
                        }
                      }
                    ],
                    "尝试攀爬": [
                      {
                        "id": 30026,
                        "chr": "1",
                        "txt": "我得试着抓住旁边的岩石，慢慢爬上去。",
                        "opt": {
                          "攀爬成功": [
                            {
                              "id": 30027,
                              "chr": "0",
                              "txt": "太好了，我成功爬上来了！"
                            }
                          ],
                          "攀爬失败": [
                            {
                              "id": 30028,
                              "chr": "0",
                              "txt": "该死，岩石太滑了，我掉了下去！"
                            }
                          ]
                        }
                      }
                    ]
                  }
                ]
              }
            }
          ],
          "绕过裂缝": [
            {
              "id": 30029,
              "chr": "1",
              "txt": "我得绕过它，不能冒险跳过去。",
              "opt": {
                "成功绕过": [
                  {
                    "id": 30030,
                    "chr": "0",
                    "txt": "绕了一段路，但最终我还是绕过了裂缝。"
                  }
                ],
                "遭遇障碍": [
                  {
                    "id": 30031,
                    "chr": "0",
                    "txt": "前面被巨大的岩石挡住了路，我必须回去重新找办法。"
                  }
                ]
              }
            }
          ]
        }
      }
    ]
  },
  "失落的记忆": {
    "cap": "发现遗失的回忆",
    "pgrs": 4.0,
    "dia": [
      {
        "id": 40000,
        "txt": "你找到了一个破旧的盒子，里面装着什么？",
        "opt": {
          "打开盒子": [
            {
              "id": 40001,
              "chr": "1",
              "txt": "里面有一张旧照片和一封信。",
              "opt": {
                "查看照片": [
                  {
                    "id": 40002,
                    "chr": "0",
                    "txt": "这是一张我们小时候的合照，我完全忘记了它的存在。"
                  }
                ],
                "阅读信件": [
                  {
                    "id": 40003,
                    "chr": "0",
                    "txt": "信里写着一些我完全不记得的事情，它们好像不属于我的记忆。"
                  }
                ]
              }
            }
          ],
          "不要打开": [
            {
              "id": 40004,
              "chr": "1",
              "txt": "也许有些事情不该被揭开，还是让它保持原样吧。",
              "opt": {
                "坚持不开": [
                  {
                    "id": 40005,
                    "chr": "0",
                    "txt": "我决定不打开它，任由它继续掩埋在时间中。"
                  }
                ],
                "改变主意": [
                  {
                    "id": 40006,
                    "chr": "0",
                    "txt": "不过...好奇心最终战胜了我，我还是打开了它。"
                  }
                ]
              }
            }
          ]
        }
      },
      {
        "id": 40007,
        "txt": "突然，天空开始变得昏暗，这片回忆中的世界好像在崩塌。",
        "opt": {
          "寻找出口": [
            {
              "id": 40008,
              "chr": "1",
              "txt": "我必须尽快离开这里，这里不再安全。",
              "opt": {
                "成功逃脱": [
                  {
                    "id": 40009,
                    "chr": "0",
                    "txt": "我最终找到了出口，逃离了这场崩塌。"
                  }
                ],
                "陷入困境": [
                  {
                    "id": 40010,
                    "chr": "0",
                    "txt": "该死，路已经被堵住了，我无路可逃。"
                  }
                ]
              }
            }
          ],
          "停下来观察": [
            {
              "id": 40011,
              "chr": "1",
              "txt": "这里的变化太诡异了，我必须弄清楚发生了什么。",
              "opt": {
                "发现原因": [
                  {
                    "id": 40012,
                    "chr": "0",
                    "txt": "原来这一切都只是我的内心在崩溃。"
                  }
                ],
                "什么也没发现": [
                  {
                    "id": 40013,
                    "chr": "0",
                    "txt": "我找不到任何线索，只能无奈地看着世界崩塌。"
                  }
                ]
              }
            }
          ]
        }
      }
    ]
  }
}

                 